csi.py
cloudshell_interface-0.1.1.dist-info/METADATA
cloudshell_interface-0.1.1.dist-info/WHEEL
cloudshell_interface-0.1.1.dist-info/entry_points.txt
cloudshell_interface-0.1.1.dist-info/licenses/LICENSE
cloudshell_interface-0.1.1.dist-info/RECORD
