Metadata-Version: 2.4
Name: cloudshell-interface
Version: 0.1.1
Summary: CLI for AWS CloudShell
Project-URL: Homepage, https://github.com/itsjfx/csi
Project-URL: Repository, https://github.com/itsjfx/csi
Project-URL: Issues, https://github.com/itsjfx/csi/issues
Author-email: Thomas <me@jfx.ac>
License-Expression: GPL-3.0-or-later
License-File: LICENSE
Keywords: aws,cli,cloudshell,ssm,vpc
Classifier: Development Status :: 4 - Beta
Classifier: Intended Audience :: Developers
Classifier: Intended Audience :: System Administrators
Classifier: License :: OSI Approved :: GNU General Public License v3 or later (GPLv3+)
Classifier: Programming Language :: Python :: 3
Classifier: Programming Language :: Python :: 3.13
Classifier: Topic :: System :: Systems Administration
Classifier: Topic :: Utilities
Requires-Python: >=3.13
Requires-Dist: boto3>=1.40.52
Requires-Dist: botocore>=1.40.52
Requires-Dist: requests>=2.32.5
Provides-Extra: dev
Requires-Dist: shtab>=1.7.1; extra == 'dev'
